{
    "id": "a75e9c5Intro3Phys10b",
    "stepAnswer": [
        "$$3.13$$"
    ],
    "problemType": "TextBox",
    "stepTitle": "Standing at the base of one of the cliffs of Mt. Arapiles in Victoria, Australia, a hiker hears a rock break loose from a height of $$105$$ $$m$$. He can\u2019t see the rock right away but then does, $$1.50$$ s later. How much time does he have to move before the rock hits his head?",
    "stepBody": "",
    "answerType": "arithmetic",
    "variabilization": {},
    "answerLatex": "$$3.13$$"
}